report/__init__.py
report/report.py
report_monaco-0.0.4.dist-info/LICENSE
report_monaco-0.0.4.dist-info/METADATA
report_monaco-0.0.4.dist-info/WHEEL
report_monaco-0.0.4.dist-info/top_level.txt
report_monaco-0.0.4.dist-info/RECORD
