Metadata-Version: 2.1
Name: report-monaco
Version: 0.0.4
Summary: Report of Monaco Q1 stage
Home-page: https://git.foxminded.com.ua/pavlo_tsiurupa/task-6-report-monaco-f1
Author: St_Paul
Author-email: pavlotsiurupaa@gmail.com
Classifier: Programming Language :: Python :: 3
Classifier: License :: OSI Approved :: MIT License
Classifier: Operating System :: OS Independent
Requires-Python: >=3.6
License-File: LICENSE
